WheelGen/__init__.py
WheelGen/gear_ops.py
WheelGen/materials.py
WheelGen/props.py
WheelGen/ui_panel.py
WheelGen/utils.py
WheelGen/wheel_ops.py
wheel_generator-1.1.1.dist-info/licenses/LICENSE
wheel_generator-1.1.1.dist-info/METADATA
wheel_generator-1.1.1.dist-info/WHEEL
wheel_generator-1.1.1.dist-info/top_level.txt
wheel_generator-1.1.1.dist-info/RECORD
